Metadata-Version: 2.1
Name: find-word
Version: 1.2
Summary: search by word
Home-page: https://github.com/PanovAlexsandr
Author: Alexsus
Author-email: aleksandr.panov2000@yandex.ru
License: UNKNOWN
Platform: UNKNOWN
Classifier: Programming Language :: Python :: 3
Classifier: License :: OSI Approved :: MIT License
Classifier: Operating System :: OS Independent
Requires-Python: >=3.9
